redis_work_queue/__init__.py
redis_work_queue/item.py
redis_work_queue/keyprefix.py
redis_work_queue/workqueue.py
redis_work_queue-0.1.5.dist-info/LICENSE
redis_work_queue-0.1.5.dist-info/METADATA
redis_work_queue-0.1.5.dist-info/WHEEL
redis_work_queue-0.1.5.dist-info/top_level.txt
redis_work_queue-0.1.5.dist-info/RECORD
