Metadata-Version: 2.1
Name: redis-work-queue
Version: 0.1.5
Summary: A work queue, on top of a redis database, with implementations in Python, Rust, Go, Node.js (TypeScript) and Dotnet (C#).
Author-email: Jacob O'Toole <jacob.otoole@mevitae.com>
License: Copyright 2023 Jacob O'Toole
Classifier: Programming Language :: Python :: 3
Classifier: License :: OSI Approved :: MIT License
Classifier: Operating System :: OS Independent
License-File: LICENSE
Requires-Dist: redis
Requires-Dist: uuid
